[
  {
    "op_type": 0,
    "data_type": 1,
    "in_h": 224,
    "in_w": 224,
    "in_c": 3,
    "out_h": 112,
    "out_w": 112,
    "out_c": 56,
    "kernel_h": 3,
    "kernel_w": 3,
    "stride_h": 2,
    "stride_w": 2,
    "pad_top": 1,
    "pad_left": 1,
    "k_depth": 27,
    "post_ctrl": 196,
    "relu6": false,
    "pool_cfg": 0,
    "resize_cfg": 0,
    "deconv_cfg": 0,
    "concat_cfg": 0,
    "dma_in_size": 361592,
    "dma_wgt_size": 3024,
    "wgt_per_oc_words": 0,
    "dma_out_size": 1792,
    "dma_param_count": 56,
    "tile_in_size": 2348,
    "tile_out_size": 0,
    "store_mode": 0,
    "row_cfg": 0,
    "n_input_words": 587,
    "n_output_words": 448,
    "tile_h": 8,
    "tile_w": 11,
    "tile_num_h": 14,
    "tile_num_w": 11,
    "sched_ctrl": 1,
    "ddr_in_addr": 805306368,
    "ddr_out_addr": 805679104,
    "ddr_wgt_addr": 805670912,
    "ddr_param_addr": 805675008,
    "clamp_min": -32768,
    "clamp_max": 32767,
    "in_zp": 0,
    "input_src": -1,
    "residual_src": -1
  },
  {
    "op_type": 1,
    "data_type": 1,
    "in_h": 112,
    "in_w": 112,
    "in_c": 56,
    "out_h": 112,
    "out_w": 112,
    "out_c": 56,
    "kernel_h": 3,
    "kernel_w": 3,
    "stride_h": 1,
    "stride_w": 1,
    "pad_top": 1,
    "pad_left": 1,
    "k_depth": 9,
    "post_ctrl": 196,
    "relu6": false,
    "pool_cfg": 0,
    "resize_cfg": 0,
    "deconv_cfg": 0,
    "concat_cfg": 0,
    "dma_in_size": 2587648,
    "dma_wgt_size": 1008,
    "wgt_per_oc_words": 0,
    "dma_out_size": 1792,
    "dma_param_count": 56,
    "tile_in_size": 7168,
    "tile_out_size": 0,
    "store_mode": 0,
    "row_cfg": 0,
    "n_input_words": 1792,
    "n_output_words": 448,
    "tile_h": 6,
    "tile_w": 6,
    "tile_num_h": 19,
    "tile_num_w": 19,
    "sched_ctrl": 1,
    "ddr_in_addr": 805683200,
    "ddr_out_addr": 808280064,
    "ddr_wgt_addr": 808271872,
    "ddr_param_addr": 808275968,
    "clamp_min": -32768,
    "clamp_max": 32767,
    "in_zp": 0,
    "input_src": -1,
    "residual_src": -1
  },
  {
    "op_type": 0,
    "data_type": 1,
    "in_h": 112,
    "in_w": 112,
    "in_c": 56,
    "out_h": 112,
    "out_w": 112,
    "out_c": 56,
    "kernel_h": 1,
    "kernel_w": 1,
    "stride_h": 1,
    "stride_w": 1,
    "pad_top": 0,
    "pad_left": 0,
    "k_depth": 56,
    "post_ctrl": 196,
    "relu6": false,
    "pool_cfg": 0,
    "resize_cfg": 0,
    "deconv_cfg": 0,
    "concat_cfg": 0,
    "dma_in_size": 1493856,
    "dma_wgt_size": 6272,
    "wgt_per_oc_words": 0,
    "dma_out_size": 1792,
    "dma_param_count": 56,
    "tile_in_size": 6048,
    "tile_out_size": 0,
    "store_mode": 0,
    "row_cfg": 0,
    "n_input_words": 1512,
    "n_output_words": 448,
    "tile_h": 6,
    "tile_w": 9,
    "tile_num_h": 19,
    "tile_num_w": 13,
    "sched_ctrl": 1,
    "ddr_in_addr": 808284160,
    "ddr_out_addr": 809791488,
    "ddr_wgt_addr": 809779200,
    "ddr_param_addr": 809787392,
    "clamp_min": -32768,
    "clamp_max": 32767,
    "in_zp": 0,
    "input_src": -1,
    "residual_src": -1
  },
  {
    "op_type": 0,
    "data_type": 1,
    "in_h": 112,
    "in_w": 112,
    "in_c": 56,
    "out_h": 112,
    "out_w": 112,
    "out_c": 112,
    "kernel_h": 1,
    "kernel_w": 1,
    "stride_h": 1,
    "stride_w": 1,
    "pad_top": 0,
    "pad_left": 0,
    "k_depth": 56,
    "post_ctrl": 196,
    "relu6": false,
    "pool_cfg": 0,
    "resize_cfg": 0,
    "deconv_cfg": 0,
    "concat_cfg": 0,
    "dma_in_size": 1455552,
    "dma_wgt_size": 12544,
    "wgt_per_oc_words": 0,
    "dma_out_size": 3584,
    "dma_param_count": 112,
    "tile_in_size": 4032,
    "tile_out_size": 0,
    "store_mode": 0,
    "row_cfg": 0,
    "n_input_words": 1008,
    "n_output_words": 896,
    "tile_h": 6,
    "tile_w": 6,
    "tile_num_h": 19,
    "tile_num_w": 19,
    "sched_ctrl": 1,
    "ddr_in_addr": 809795584,
    "ddr_out_addr": 811274240,
    "ddr_wgt_addr": 811253760,
    "ddr_param_addr": 811270144,
    "clamp_min": -32768,
    "clamp_max": 32767,
    "in_zp": 0,
    "input_src": -1,
    "residual_src": -1
  },
  {
    "op_type": 1,
    "data_type": 1,
    "in_h": 112,
    "in_w": 112,
    "in_c": 112,
    "out_h": 56,
    "out_w": 56,
    "out_c": 112,
    "kernel_h": 3,
    "kernel_w": 3,
    "stride_h": 2,
    "stride_w": 2,
    "pad_top": 1,
    "pad_left": 1,
    "k_depth": 9,
    "post_ctrl": 196,
    "relu6": false,
    "pool_cfg": 0,
    "resize_cfg": 0,
    "deconv_cfg": 0,
    "concat_cfg": 0,
    "dma_in_size": 3951360,
    "dma_wgt_size": 2016,
    "wgt_per_oc_words": 0,
    "dma_out_size": 1792,
    "dma_param_count": 112,
    "tile_in_size": 10080,
    "tile_out_size": 0,
    "store_mode": 0,
    "row_cfg": 0,
    "n_input_words": 2520,
    "n_output_words": 448,
    "tile_h": 2,
    "tile_w": 4,
    "tile_num_h": 28,
    "tile_num_w": 14,
    "sched_ctrl": 1,
    "ddr_in_addr": 811278336,
    "ddr_out_addr": 815239168,
    "ddr_wgt_addr": 815230976,
    "ddr_param_addr": 815235072,
    "clamp_min": -32768,
    "clamp_max": 32767,
    "in_zp": 0,
    "input_src": -1,
    "residual_src": -1
  },
  {
    "op_type": 0,
    "data_type": 1,
    "in_h": 56,
    "in_w": 56,
    "in_c": 112,
    "out_h": 56,
    "out_w": 56,
    "out_c": 56,
    "kernel_h": 1,
    "kernel_w": 1,
    "stride_h": 1,
    "stride_w": 1,
    "pad_top": 0,
    "pad_left": 0,
    "k_depth": 112,
    "post_ctrl": 192,
    "relu6": false,
    "pool_cfg": 0,
    "resize_cfg": 0,
    "deconv_cfg": 0,
    "concat_cfg": 0,
    "dma_in_size": 806400,
    "dma_wgt_size": 12544,
    "wgt_per_oc_words": 0,
    "dma_out_size": 448,
    "dma_param_count": 56,
    "tile_in_size": 8064,
    "tile_out_size": 0,
    "store_mode": 0,
    "row_cfg": 0,
    "n_input_words": 2016,
    "n_output_words": 112,
    "tile_h": 6,
    "tile_w": 6,
    "tile_num_h": 10,
    "tile_num_w": 10,
    "sched_ctrl": 1,
    "ddr_in_addr": 815243264,
    "ddr_out_addr": 816070656,
    "ddr_wgt_addr": 816050176,
    "ddr_param_addr": 816066560,
    "clamp_min": -32768,
    "clamp_max": 32767,
    "in_zp": 0,
    "input_src": -1,
    "residual_src": -1
  },
  {
    "op_type": 0,
    "data_type": 1,
    "in_h": 56,
    "in_w": 56,
    "in_c": 56,
    "out_h": 56,
    "out_w": 56,
    "out_c": 112,
    "kernel_h": 1,
    "kernel_w": 1,
    "stride_h": 1,
    "stride_w": 1,
    "pad_top": 0,
    "pad_left": 0,
    "k_depth": 56,
    "post_ctrl": 196,
    "relu6": false,
    "pool_cfg": 0,
    "resize_cfg": 0,
    "deconv_cfg": 0,
    "concat_cfg": 0,
    "dma_in_size": 351232,
    "dma_wgt_size": 12544,
    "wgt_per_oc_words": 0,
    "dma_out_size": 14336,
    "dma_param_count": 112,
    "tile_in_size": 7168,
    "tile_out_size": 0,
    "store_mode": 0,
    "row_cfg": 0,
    "n_input_words": 1792,
    "n_output_words": 3584,
    "tile_h": 8,
    "tile_w": 8,
    "tile_num_h": 7,
    "tile_num_w": 7,
    "sched_ctrl": 1,
    "ddr_in_addr": 816074752,
    "ddr_out_addr": 816447488,
    "ddr_wgt_addr": 816427008,
    "ddr_param_addr": 816443392,
    "clamp_min": -32768,
    "clamp_max": 32767,
    "in_zp": 0,
    "input_src": -1,
    "residual_src": -1
  },
  {
    "op_type": 1,
    "data_type": 1,
    "in_h": 56,
    "in_w": 56,
    "in_c": 112,
    "out_h": 56,
    "out_w": 56,
    "out_c": 112,
    "kernel_h": 3,
    "kernel_w": 3,
    "stride_h": 1,
    "stride_w": 1,
    "pad_top": 1,
    "pad_left": 1,
    "k_depth": 9,
    "post_ctrl": 196,
    "relu6": false,
    "pool_cfg": 0,
    "resize_cfg": 0,
    "deconv_cfg": 0,
    "concat_cfg": 0,
    "dma_in_size": 1580544,
    "dma_wgt_size": 2016,
    "wgt_per_oc_words": 0,
    "dma_out_size": 3584,
    "dma_param_count": 112,
    "tile_in_size": 8064,
    "tile_out_size": 0,
    "store_mode": 0,
    "row_cfg": 0,
    "n_input_words": 2016,
    "n_output_words": 896,
    "tile_h": 4,
    "tile_w": 4,
    "tile_num_h": 14,
    "tile_num_w": 14,
    "sched_ctrl": 1,
    "ddr_in_addr": 816463872,
    "ddr_out_addr": 818053120,
    "ddr_wgt_addr": 818044928,
    "ddr_param_addr": 818049024,
    "clamp_min": -32768,
    "clamp_max": 32767,
    "in_zp": 0,
    "input_src": -1,
    "residual_src": -1
  },
  {
    "op_type": 0,
    "data_type": 1,
    "in_h": 56,
    "in_w": 56,
    "in_c": 112,
    "out_h": 56,
    "out_w": 56,
    "out_c": 56,
    "kernel_h": 1,
    "kernel_w": 1,
    "stride_h": 1,
    "stride_w": 1,
    "pad_top": 0,
    "pad_left": 0,
    "k_depth": 112,
    "post_ctrl": 192,
    "relu6": false,
    "pool_cfg": 0,
    "resize_cfg": 0,
    "deconv_cfg": 0,
    "concat_cfg": 0,
    "dma_in_size": 806400,
    "dma_wgt_size": 12544,
    "wgt_per_oc_words": 0,
    "dma_out_size": 448,
    "dma_param_count": 56,
    "tile_in_size": 8064,
    "tile_out_size": 0,
    "store_mode": 0,
    "row_cfg": 0,
    "n_input_words": 2016,
    "n_output_words": 112,
    "tile_h": 6,
    "tile_w": 6,
    "tile_num_h": 10,
    "tile_num_w": 10,
    "sched_ctrl": 1,
    "ddr_in_addr": 818057216,
    "ddr_out_addr": 818884608,
    "ddr_wgt_addr": 818864128,
    "ddr_param_addr": 818880512,
    "clamp_min": -32768,
    "clamp_max": 32767,
    "in_zp": 0,
    "input_src": -1,
    "residual_src": -1
  },
  {
    "op_type": 4,
    "data_type": 1,
    "in_h": 56,
    "in_w": 56,
    "in_c": 56,
    "out_h": 56,
    "out_w": 56,
    "out_c": 56,
    "kernel_h": 1,
    "kernel_w": 1,
    "stride_h": 1,
    "stride_w": 1,
    "pad_top": 0,
    "pad_left": 0,
    "k_depth": 1,
    "post_ctrl": 129,
    "relu6": false,
    "pool_cfg": 0,
    "resize_cfg": 0,
    "deconv_cfg": 0,
    "concat_cfg": 0,
    "dma_in_size": 423360,
    "dma_wgt_size": 0,
    "wgt_per_oc_words": 0,
    "dma_out_size": 448,
    "dma_param_count": 2,
    "tile_in_size": 6048,
    "tile_out_size": 0,
    "store_mode": 0,
    "row_cfg": 0,
    "n_input_words": 1512,
    "n_output_words": 112,
    "tile_h": 6,
    "tile_w": 9,
    "tile_num_h": 10,
    "tile_num_w": 7,
    "sched_ctrl": 1,
    "ddr_in_addr": 818888704,
    "ddr_out_addr": 819748864,
    "ddr_wgt_addr": 819740672,
    "ddr_param_addr": 819744768,
    "clamp_min": -32768,
    "clamp_max": 32767,
    "in_zp": 0,
    "input_src": -1,
    "residual_src": 5,
    "add_M_A": 27419,
    "add_S_A": 15,
    "add_M_B": 26450,
    "add_S_B": 15,
    "ddr_add_b_addr": 819314688
  },
  {
    "op_type": 0,
    "data_type": 1,
    "in_h": 56,
    "in_w": 56,
    "in_c": 56,
    "out_h": 56,
    "out_w": 56,
    "out_c": 112,
    "kernel_h": 1,
    "kernel_w": 1,
    "stride_h": 1,
    "stride_w": 1,
    "pad_top": 0,
    "pad_left": 0,
    "k_depth": 56,
    "post_ctrl": 196,
    "relu6": false,
    "pool_cfg": 0,
    "resize_cfg": 0,
    "deconv_cfg": 0,
    "concat_cfg": 0,
    "dma_in_size": 351232,
    "dma_wgt_size": 12544,
    "wgt_per_oc_words": 0,
    "dma_out_size": 14336,
    "dma_param_count": 112,
    "tile_in_size": 7168,
    "tile_out_size": 0,
    "store_mode": 0,
    "row_cfg": 0,
    "n_input_words": 1792,
    "n_output_words": 3584,
    "tile_h": 8,
    "tile_w": 8,
    "tile_num_h": 7,
    "tile_num_w": 7,
    "sched_ctrl": 1,
    "ddr_in_addr": 819326976,
    "ddr_out_addr": 819699712,
    "ddr_wgt_addr": 819679232,
    "ddr_param_addr": 819695616,
    "clamp_min": -32768,
    "clamp_max": 32767,
    "in_zp": 0,
    "input_src": -1,
    "residual_src": -1
  },
  {
    "op_type": 1,
    "data_type": 1,
    "in_h": 56,
    "in_w": 56,
    "in_c": 112,
    "out_h": 56,
    "out_w": 56,
    "out_c": 112,
    "kernel_h": 3,
    "kernel_w": 3,
    "stride_h": 1,
    "stride_w": 1,
    "pad_top": 1,
    "pad_left": 1,
    "k_depth": 9,
    "post_ctrl": 196,
    "relu6": false,
    "pool_cfg": 0,
    "resize_cfg": 0,
    "deconv_cfg": 0,
    "concat_cfg": 0,
    "dma_in_size": 1580544,
    "dma_wgt_size": 2016,
    "wgt_per_oc_words": 0,
    "dma_out_size": 3584,
    "dma_param_count": 112,
    "tile_in_size": 8064,
    "tile_out_size": 0,
    "store_mode": 0,
    "row_cfg": 0,
    "n_input_words": 2016,
    "n_output_words": 896,
    "tile_h": 4,
    "tile_w": 4,
    "tile_num_h": 14,
    "tile_num_w": 14,
    "sched_ctrl": 1,
    "ddr_in_addr": 819716096,
    "ddr_out_addr": 821305344,
    "ddr_wgt_addr": 821297152,
    "ddr_param_addr": 821301248,
    "clamp_min": -32768,
    "clamp_max": 32767,
    "in_zp": 0,
    "input_src": -1,
    "residual_src": -1
  },
  {
    "op_type": 0,
    "data_type": 1,
    "in_h": 56,
    "in_w": 56,
    "in_c": 112,
    "out_h": 56,
    "out_w": 56,
    "out_c": 56,
    "kernel_h": 1,
    "kernel_w": 1,
    "stride_h": 1,
    "stride_w": 1,
    "pad_top": 0,
    "pad_left": 0,
    "k_depth": 112,
    "post_ctrl": 192,
    "relu6": false,
    "pool_cfg": 0,
    "resize_cfg": 0,
    "deconv_cfg": 0,
    "concat_cfg": 0,
    "dma_in_size": 806400,
    "dma_wgt_size": 12544,
    "wgt_per_oc_words": 0,
    "dma_out_size": 448,
    "dma_param_count": 56,
    "tile_in_size": 8064,
    "tile_out_size": 0,
    "store_mode": 0,
    "row_cfg": 0,
    "n_input_words": 2016,
    "n_output_words": 112,
    "tile_h": 6,
    "tile_w": 6,
    "tile_num_h": 10,
    "tile_num_w": 10,
    "sched_ctrl": 1,
    "ddr_in_addr": 821309440,
    "ddr_out_addr": 822136832,
    "ddr_wgt_addr": 822116352,
    "ddr_param_addr": 822132736,
    "clamp_min": -32768,
    "clamp_max": 32767,
    "in_zp": 0,
    "input_src": -1,
    "residual_src": -1
  },
  {
    "op_type": 4,
    "data_type": 1,
    "in_h": 56,
    "in_w": 56,
    "in_c": 56,
    "out_h": 56,
    "out_w": 56,
    "out_c": 56,
    "kernel_h": 1,
    "kernel_w": 1,
    "stride_h": 1,
    "stride_w": 1,
    "pad_top": 0,
    "pad_left": 0,
    "k_depth": 1,
    "post_ctrl": 129,
    "relu6": false,
    "pool_cfg": 0,
    "resize_cfg": 0,
    "deconv_cfg": 0,
    "concat_cfg": 0,
    "dma_in_size": 423360,
    "dma_wgt_size": 0,
    "wgt_per_oc_words": 0,
    "dma_out_size": 448,
    "dma_param_count": 2,
    "tile_in_size": 6048,
    "tile_out_size": 0,
    "store_mode": 0,
    "row_cfg": 0,
    "n_input_words": 1512,
    "n_output_words": 112,
    "tile_h": 6,
    "tile_w": 9,
    "tile_num_h": 10,
    "tile_num_w": 7,
    "sched_ctrl": 1,
    "ddr_in_addr": 822140928,
    "ddr_out_addr": 823001088,
    "ddr_wgt_addr": 822992896,
    "ddr_param_addr": 822996992,
    "clamp_min": -32768,
    "clamp_max": 32767,
    "in_zp": 0,
    "input_src": -1,
    "residual_src": 9,
    "add_M_A": 22883,
    "add_S_A": 15,
    "add_M_B": 20755,
    "add_S_B": 15,
    "ddr_add_b_addr": 822566912
  },
  {
    "op_type": 0,
    "data_type": 1,
    "in_h": 56,
    "in_w": 56,
    "in_c": 56,
    "out_h": 56,
    "out_w": 56,
    "out_c": 112,
    "kernel_h": 1,
    "kernel_w": 1,
    "stride_h": 1,
    "stride_w": 1,
    "pad_top": 0,
    "pad_left": 0,
    "k_depth": 56,
    "post_ctrl": 196,
    "relu6": false,
    "pool_cfg": 0,
    "resize_cfg": 0,
    "deconv_cfg": 0,
    "concat_cfg": 0,
    "dma_in_size": 351232,
    "dma_wgt_size": 12544,
    "wgt_per_oc_words": 0,
    "dma_out_size": 14336,
    "dma_param_count": 112,
    "tile_in_size": 7168,
    "tile_out_size": 0,
    "store_mode": 0,
    "row_cfg": 0,
    "n_input_words": 1792,
    "n_output_words": 3584,
    "tile_h": 8,
    "tile_w": 8,
    "tile_num_h": 7,
    "tile_num_w": 7,
    "sched_ctrl": 1,
    "ddr_in_addr": 822579200,
    "ddr_out_addr": 822951936,
    "ddr_wgt_addr": 822931456,
    "ddr_param_addr": 822947840,
    "clamp_min": -32768,
    "clamp_max": 32767,
    "in_zp": 0,
    "input_src": -1,
    "residual_src": -1
  },
  {
    "op_type": 1,
    "data_type": 1,
    "in_h": 56,
    "in_w": 56,
    "in_c": 112,
    "out_h": 56,
    "out_w": 56,
    "out_c": 112,
    "kernel_h": 3,
    "kernel_w": 3,
    "stride_h": 1,
    "stride_w": 1,
    "pad_top": 1,
    "pad_left": 1,
    "k_depth": 9,
    "post_ctrl": 196,
    "relu6": false,
    "pool_cfg": 0,
    "resize_cfg": 0,
    "deconv_cfg": 0,
    "concat_cfg": 0,
    "dma_in_size": 1580544,
    "dma_wgt_size": 2016,
    "wgt_per_oc_words": 0,
    "dma_out_size": 3584,
    "dma_param_count": 112,
    "tile_in_size": 8064,
    "tile_out_size": 0,
    "store_mode": 0,
    "row_cfg": 0,
    "n_input_words": 2016,
    "n_output_words": 896,
    "tile_h": 4,
    "tile_w": 4,
    "tile_num_h": 14,
    "tile_num_w": 14,
    "sched_ctrl": 1,
    "ddr_in_addr": 822968320,
    "ddr_out_addr": 824557568,
    "ddr_wgt_addr": 824549376,
    "ddr_param_addr": 824553472,
    "clamp_min": -32768,
    "clamp_max": 32767,
    "in_zp": 0,
    "input_src": -1,
    "residual_src": -1
  },
  {
    "op_type": 0,
    "data_type": 1,
    "in_h": 56,
    "in_w": 56,
    "in_c": 112,
    "out_h": 56,
    "out_w": 56,
    "out_c": 56,
    "kernel_h": 1,
    "kernel_w": 1,
    "stride_h": 1,
    "stride_w": 1,
    "pad_top": 0,
    "pad_left": 0,
    "k_depth": 112,
    "post_ctrl": 192,
    "relu6": false,
    "pool_cfg": 0,
    "resize_cfg": 0,
    "deconv_cfg": 0,
    "concat_cfg": 0,
    "dma_in_size": 806400,
    "dma_wgt_size": 12544,
    "wgt_per_oc_words": 0,
    "dma_out_size": 448,
    "dma_param_count": 56,
    "tile_in_size": 8064,
    "tile_out_size": 0,
    "store_mode": 0,
    "row_cfg": 0,
    "n_input_words": 2016,
    "n_output_words": 112,
    "tile_h": 6,
    "tile_w": 6,
    "tile_num_h": 10,
    "tile_num_w": 10,
    "sched_ctrl": 1,
    "ddr_in_addr": 824561664,
    "ddr_out_addr": 825389056,
    "ddr_wgt_addr": 825368576,
    "ddr_param_addr": 825384960,
    "clamp_min": -32768,
    "clamp_max": 32767,
    "in_zp": 0,
    "input_src": -1,
    "residual_src": -1
  },
  {
    "op_type": 4,
    "data_type": 1,
    "in_h": 56,
    "in_w": 56,
    "in_c": 56,
    "out_h": 56,
    "out_w": 56,
    "out_c": 56,
    "kernel_h": 1,
    "kernel_w": 1,
    "stride_h": 1,
    "stride_w": 1,
    "pad_top": 0,
    "pad_left": 0,
    "k_depth": 1,
    "post_ctrl": 129,
    "relu6": false,
    "pool_cfg": 0,
    "resize_cfg": 0,
    "deconv_cfg": 0,
    "concat_cfg": 0,
    "dma_in_size": 423360,
    "dma_wgt_size": 0,
    "wgt_per_oc_words": 0,
    "dma_out_size": 448,
    "dma_param_count": 2,
    "tile_in_size": 6048,
    "tile_out_size": 0,
    "store_mode": 0,
    "row_cfg": 0,
    "n_input_words": 1512,
    "n_output_words": 112,
    "tile_h": 6,
    "tile_w": 9,
    "tile_num_h": 10,
    "tile_num_w": 7,
    "sched_ctrl": 1,
    "ddr_in_addr": 825393152,
    "ddr_out_addr": 826253312,
    "ddr_wgt_addr": 826245120,
    "ddr_param_addr": 826249216,
    "clamp_min": -32768,
    "clamp_max": 32767,
    "in_zp": 0,
    "input_src": -1,
    "residual_src": 13,
    "add_M_A": 29515,
    "add_S_A": 15,
    "add_M_B": 23766,
    "add_S_B": 15,
    "ddr_add_b_addr": 825819136
  },
  {
    "op_type": 0,
    "data_type": 1,
    "in_h": 56,
    "in_w": 56,
    "in_c": 56,
    "out_h": 56,
    "out_w": 56,
    "out_c": 112,
    "kernel_h": 1,
    "kernel_w": 1,
    "stride_h": 1,
    "stride_w": 1,
    "pad_top": 0,
    "pad_left": 0,
    "k_depth": 56,
    "post_ctrl": 196,
    "relu6": false,
    "pool_cfg": 0,
    "resize_cfg": 0,
    "deconv_cfg": 0,
    "concat_cfg": 0,
    "dma_in_size": 351232,
    "dma_wgt_size": 12544,
    "wgt_per_oc_words": 0,
    "dma_out_size": 14336,
    "dma_param_count": 112,
    "tile_in_size": 7168,
    "tile_out_size": 0,
    "store_mode": 0,
    "row_cfg": 0,
    "n_input_words": 1792,
    "n_output_words": 3584,
    "tile_h": 8,
    "tile_w": 8,
    "tile_num_h": 7,
    "tile_num_w": 7,
    "sched_ctrl": 1,
    "ddr_in_addr": 825831424,
    "ddr_out_addr": 826204160,
    "ddr_wgt_addr": 826183680,
    "ddr_param_addr": 826200064,
    "clamp_min": -32768,
    "clamp_max": 32767,
    "in_zp": 0,
    "input_src": -1,
    "residual_src": -1
  },
  {
    "op_type": 1,
    "data_type": 1,
    "in_h": 56,
    "in_w": 56,
    "in_c": 112,
    "out_h": 56,
    "out_w": 56,
    "out_c": 112,
    "kernel_h": 3,
    "kernel_w": 3,
    "stride_h": 1,
    "stride_w": 1,
    "pad_top": 1,
    "pad_left": 1,
    "k_depth": 9,
    "post_ctrl": 196,
    "relu6": false,
    "pool_cfg": 0,
    "resize_cfg": 0,
    "deconv_cfg": 0,
    "concat_cfg": 0,
    "dma_in_size": 1580544,
    "dma_wgt_size": 2016,
    "wgt_per_oc_words": 0,
    "dma_out_size": 3584,
    "dma_param_count": 112,
    "tile_in_size": 8064,
    "tile_out_size": 0,
    "store_mode": 0,
    "row_cfg": 0,
    "n_input_words": 2016,
    "n_output_words": 896,
    "tile_h": 4,
    "tile_w": 4,
    "tile_num_h": 14,
    "tile_num_w": 14,
    "sched_ctrl": 1,
    "ddr_in_addr": 826220544,
    "ddr_out_addr": 827809792,
    "ddr_wgt_addr": 827801600,
    "ddr_param_addr": 827805696,
    "clamp_min": -32768,
    "clamp_max": 32767,
    "in_zp": 0,
    "input_src": -1,
    "residual_src": -1
  },
  {
    "op_type": 0,
    "data_type": 1,
    "in_h": 56,
    "in_w": 56,
    "in_c": 112,
    "out_h": 56,
    "out_w": 56,
    "out_c": 56,
    "kernel_h": 1,
    "kernel_w": 1,
    "stride_h": 1,
    "stride_w": 1,
    "pad_top": 0,
    "pad_left": 0,
    "k_depth": 112,
    "post_ctrl": 192,
    "relu6": false,
    "pool_cfg": 0,
    "resize_cfg": 0,
    "deconv_cfg": 0,
    "concat_cfg": 0,
    "dma_in_size": 806400,
    "dma_wgt_size": 12544,
    "wgt_per_oc_words": 0,
    "dma_out_size": 448,
    "dma_param_count": 56,
    "tile_in_size": 8064,
    "tile_out_size": 0,
    "store_mode": 0,
    "row_cfg": 0,
    "n_input_words": 2016,
    "n_output_words": 112,
    "tile_h": 6,
    "tile_w": 6,
    "tile_num_h": 10,
    "tile_num_w": 10,
    "sched_ctrl": 1,
    "ddr_in_addr": 827813888,
    "ddr_out_addr": 828641280,
    "ddr_wgt_addr": 828620800,
    "ddr_param_addr": 828637184,
    "clamp_min": -32768,
    "clamp_max": 32767,
    "in_zp": 0,
    "input_src": -1,
    "residual_src": -1
  },
  {
    "op_type": 4,
    "data_type": 1,
    "in_h": 56,
    "in_w": 56,
    "in_c": 56,
    "out_h": 56,
    "out_w": 56,
    "out_c": 56,
    "kernel_h": 1,
    "kernel_w": 1,
    "stride_h": 1,
    "stride_w": 1,
    "pad_top": 0,
    "pad_left": 0,
    "k_depth": 1,
    "post_ctrl": 129,
    "relu6": false,
    "pool_cfg": 0,
    "resize_cfg": 0,
    "deconv_cfg": 0,
    "concat_cfg": 0,
    "dma_in_size": 423360,
    "dma_wgt_size": 0,
    "wgt_per_oc_words": 0,
    "dma_out_size": 448,
    "dma_param_count": 2,
    "tile_in_size": 6048,
    "tile_out_size": 0,
    "store_mode": 0,
    "row_cfg": 0,
    "n_input_words": 1512,
    "n_output_words": 112,
    "tile_h": 6,
    "tile_w": 9,
    "tile_num_h": 10,
    "tile_num_w": 7,
    "sched_ctrl": 1,
    "ddr_in_addr": 828645376,
    "ddr_out_addr": 829505536,
    "ddr_wgt_addr": 829497344,
    "ddr_param_addr": 829501440,
    "clamp_min": -32768,
    "clamp_max": 32767,
    "in_zp": 0,
    "input_src": -1,
    "residual_src": 17,
    "add_M_A": 27527,
    "add_S_A": 15,
    "add_M_B": 19331,
    "add_S_B": 15,
    "ddr_add_b_addr": 829071360
  },
  {
    "op_type": 0,
    "data_type": 1,
    "in_h": 56,
    "in_w": 56,
    "in_c": 56,
    "out_h": 56,
    "out_w": 56,
    "out_c": 224,
    "kernel_h": 1,
    "kernel_w": 1,
    "stride_h": 1,
    "stride_w": 1,
    "pad_top": 0,
    "pad_left": 0,
    "k_depth": 56,
    "post_ctrl": 196,
    "relu6": false,
    "pool_cfg": 0,
    "resize_cfg": 0,
    "deconv_cfg": 0,
    "concat_cfg": 0,
    "dma_in_size": 357504,
    "dma_wgt_size": 25088,
    "wgt_per_oc_words": 0,
    "dma_out_size": 6272,
    "dma_param_count": 224,
    "tile_in_size": 2352,
    "tile_out_size": 0,
    "store_mode": 0,
    "row_cfg": 0,
    "n_input_words": 588,
    "n_output_words": 1568,
    "tile_h": 3,
    "tile_w": 7,
    "tile_num_h": 19,
    "tile_num_w": 8,
    "sched_ctrl": 1,
    "ddr_in_addr": 829083648,
    "ddr_out_addr": 829476864,
    "ddr_wgt_addr": 829444096,
    "ddr_param_addr": 829472768,
    "clamp_min": -32768,
    "clamp_max": 32767,
    "in_zp": 0,
    "input_src": -1,
    "residual_src": -1
  },
  {
    "op_type": 1,
    "data_type": 1,
    "in_h": 56,
    "in_w": 56,
    "in_c": 224,
    "out_h": 28,
    "out_w": 28,
    "out_c": 224,
    "kernel_h": 3,
    "kernel_w": 3,
    "stride_h": 2,
    "stride_w": 2,
    "pad_top": 1,
    "pad_left": 1,
    "k_depth": 9,
    "post_ctrl": 196,
    "relu6": false,
    "pool_cfg": 0,
    "resize_cfg": 0,
    "deconv_cfg": 0,
    "concat_cfg": 0,
    "dma_in_size": 2634240,
    "dma_wgt_size": 4032,
    "wgt_per_oc_words": 0,
    "dma_out_size": 448,
    "dma_param_count": 224,
    "tile_in_size": 9408,
    "tile_out_size": 0,
    "store_mode": 0,
    "row_cfg": 0,
    "n_input_words": 2352,
    "n_output_words": 112,
    "tile_h": 1,
    "tile_w": 3,
    "tile_num_h": 28,
    "tile_num_w": 10,
    "sched_ctrl": 1,
    "ddr_in_addr": 829485056,
    "ddr_out_addr": 832131072,
    "ddr_wgt_addr": 832122880,
    "ddr_param_addr": 832126976,
    "clamp_min": -32768,
    "clamp_max": 32767,
    "in_zp": 0,
    "input_src": -1,
    "residual_src": -1
  },
  {
    "op_type": 0,
    "data_type": 1,
    "in_h": 28,
    "in_w": 28,
    "in_c": 224,
    "out_h": 28,
    "out_w": 28,
    "out_c": 96,
    "kernel_h": 1,
    "kernel_w": 1,
    "stride_h": 1,
    "stride_w": 1,
    "pad_top": 0,
    "pad_left": 0,
    "k_depth": 224,
    "post_ctrl": 192,
    "relu6": false,
    "pool_cfg": 0,
    "resize_cfg": 0,
    "deconv_cfg": 0,
    "concat_cfg": 0,
    "dma_in_size": 376320,
    "dma_wgt_size": 43008,
    "wgt_per_oc_words": 0,
    "dma_out_size": 2304,
    "dma_param_count": 96,
    "tile_in_size": 8960,
    "tile_out_size": 0,
    "store_mode": 0,
    "row_cfg": 0,
    "n_input_words": 2240,
    "n_output_words": 576,
    "tile_h": 4,
    "tile_w": 5,
    "tile_num_h": 7,
    "tile_num_w": 6,
    "sched_ctrl": 1,
    "ddr_in_addr": 832135168,
    "ddr_out_addr": 832561152,
    "ddr_wgt_addr": 832512000,
    "ddr_param_addr": 832557056,
    "clamp_min": -32768,
    "clamp_max": 32767,
    "in_zp": 0,
    "input_src": -1,
    "residual_src": -1
  },
  {
    "op_type": 0,
    "data_type": 1,
    "in_h": 28,
    "in_w": 28,
    "in_c": 96,
    "out_h": 28,
    "out_w": 28,
    "out_c": 192,
    "kernel_h": 1,
    "kernel_w": 1,
    "stride_h": 1,
    "stride_w": 1,
    "pad_top": 0,
    "pad_left": 0,
    "k_depth": 96,
    "post_ctrl": 196,
    "relu6": false,
    "pool_cfg": 0,
    "resize_cfg": 0,
    "deconv_cfg": 0,
    "concat_cfg": 0,
    "dma_in_size": 172800,
    "dma_wgt_size": 36864,
    "wgt_per_oc_words": 0,
    "dma_out_size": 6144,
    "dma_param_count": 192,
    "tile_in_size": 6912,
    "tile_out_size": 0,
    "store_mode": 0,
    "row_cfg": 0,
    "n_input_words": 1728,
    "n_output_words": 1536,
    "tile_h": 6,
    "tile_w": 6,
    "tile_num_h": 5,
    "tile_num_w": 5,
    "sched_ctrl": 1,
    "ddr_in_addr": 832565248,
    "ddr_out_addr": 832782336,
    "ddr_wgt_addr": 832741376,
    "ddr_param_addr": 832778240,
    "clamp_min": -32768,
    "clamp_max": 32767,
    "in_zp": 0,
    "input_src": -1,
    "residual_src": -1
  },
  {
    "op_type": 1,
    "data_type": 1,
    "in_h": 28,
    "in_w": 28,
    "in_c": 192,
    "out_h": 28,
    "out_w": 28,
    "out_c": 192,
    "kernel_h": 3,
    "kernel_w": 3,
    "stride_h": 1,
    "stride_w": 1,
    "pad_top": 1,
    "pad_left": 1,
    "k_depth": 9,
    "post_ctrl": 196,
    "relu6": false,
    "pool_cfg": 0,
    "resize_cfg": 0,
    "deconv_cfg": 0,
    "concat_cfg": 0,
    "dma_in_size": 903168,
    "dma_wgt_size": 3456,
    "wgt_per_oc_words": 0,
    "dma_out_size": 3072,
    "dma_param_count": 192,
    "tile_in_size": 9216,
    "tile_out_size": 0,
    "store_mode": 0,
    "row_cfg": 0,
    "n_input_words": 2304,
    "n_output_words": 768,
    "tile_h": 2,
    "tile_w": 4,
    "tile_num_h": 14,
    "tile_num_w": 7,
    "sched_ctrl": 1,
    "ddr_in_addr": 832790528,
    "ddr_out_addr": 833703936,
    "ddr_wgt_addr": 833695744,
    "ddr_param_addr": 833699840,
    "clamp_min": -32768,
    "clamp_max": 32767,
    "in_zp": 0,
    "input_src": -1,
    "residual_src": -1
  },
  {
    "op_type": 0,
    "data_type": 1,
    "in_h": 28,
    "in_w": 28,
    "in_c": 192,
    "out_h": 28,
    "out_w": 28,
    "out_c": 96,
    "kernel_h": 1,
    "kernel_w": 1,
    "stride_h": 1,
    "stride_w": 1,
    "pad_top": 0,
    "pad_left": 0,
    "k_depth": 192,
    "post_ctrl": 192,
    "relu6": false,
    "pool_cfg": 0,
    "resize_cfg": 0,
    "deconv_cfg": 0,
    "concat_cfg": 0,
    "dma_in_size": 354816,
    "dma_wgt_size": 36864,
    "wgt_per_oc_words": 0,
    "dma_out_size": 2304,
    "dma_param_count": 96,
    "tile_in_size": 8448,
    "tile_out_size": 0,
    "store_mode": 0,
    "row_cfg": 0,
    "n_input_words": 2112,
    "n_output_words": 576,
    "tile_h": 2,
    "tile_w": 11,
    "tile_num_h": 14,
    "tile_num_w": 3,
    "sched_ctrl": 1,
    "ddr_in_addr": 833708032,
    "ddr_out_addr": 834105344,
    "ddr_wgt_addr": 834064384,
    "ddr_param_addr": 834101248,
    "clamp_min": -32768,
    "clamp_max": 32767,
    "in_zp": 0,
    "input_src": -1,
    "residual_src": -1
  },
  {
    "op_type": 4,
    "data_type": 1,
    "in_h": 28,
    "in_w": 28,
    "in_c": 96,
    "out_h": 28,
    "out_w": 28,
    "out_c": 96,
    "kernel_h": 1,
    "kernel_w": 1,
    "stride_h": 1,
    "stride_w": 1,
    "pad_top": 0,
    "pad_left": 0,
    "k_depth": 1,
    "post_ctrl": 129,
    "relu6": false,
    "pool_cfg": 0,
    "resize_cfg": 0,
    "deconv_cfg": 0,
    "concat_cfg": 0,
    "dma_in_size": 172032,
    "dma_wgt_size": 0,
    "wgt_per_oc_words": 0,
    "dma_out_size": 3072,
    "dma_param_count": 2,
    "tile_in_size": 6144,
    "tile_out_size": 0,
    "store_mode": 0,
    "row_cfg": 0,
    "n_input_words": 1536,
    "n_output_words": 768,
    "tile_h": 4,
    "tile_w": 8,
    "tile_num_h": 7,
    "tile_num_w": 4,
    "sched_ctrl": 1,
    "ddr_in_addr": 834109440,
    "ddr_out_addr": 834461696,
    "ddr_wgt_addr": 834453504,
    "ddr_param_addr": 834457600,
    "clamp_min": -32768,
    "clamp_max": 32767,
    "in_zp": 0,
    "input_src": -1,
    "residual_src": 24,
    "add_M_A": 20136,
    "add_S_A": 15,
    "add_M_B": 16941,
    "add_S_B": 14,
    "ddr_add_b_addr": 834281472
  },
  {
    "op_type": 0,
    "data_type": 1,
    "in_h": 28,
    "in_w": 28,
    "in_c": 96,
    "out_h": 28,
    "out_w": 28,
    "out_c": 192,
    "kernel_h": 1,
    "kernel_w": 1,
    "stride_h": 1,
    "stride_w": 1,
    "pad_top": 0,
    "pad_left": 0,
    "k_depth": 96,
    "post_ctrl": 196,
    "relu6": false,
    "pool_cfg": 0,
    "resize_cfg": 0,
    "deconv_cfg": 0,
    "concat_cfg": 0,
    "dma_in_size": 172800,
    "dma_wgt_size": 36864,
    "wgt_per_oc_words": 0,
    "dma_out_size": 6144,
    "dma_param_count": 192,
    "tile_in_size": 6912,
    "tile_out_size": 0,
    "store_mode": 0,
    "row_cfg": 0,
    "n_input_words": 1728,
    "n_output_words": 1536,
    "tile_h": 6,
    "tile_w": 6,
    "tile_num_h": 5,
    "tile_num_w": 5,
    "sched_ctrl": 1,
    "ddr_in_addr": 834293760,
    "ddr_out_addr": 834510848,
    "ddr_wgt_addr": 834469888,
    "ddr_param_addr": 834506752,
    "clamp_min": -32768,
    "clamp_max": 32767,
    "in_zp": 0,
    "input_src": -1,
    "residual_src": -1
  },
  {
    "op_type": 1,
    "data_type": 1,
    "in_h": 28,
    "in_w": 28,
    "in_c": 192,
    "out_h": 28,
    "out_w": 28,
    "out_c": 192,
    "kernel_h": 3,
    "kernel_w": 3,
    "stride_h": 1,
    "stride_w": 1,
    "pad_top": 1,
    "pad_left": 1,
    "k_depth": 9,
    "post_ctrl": 196,
    "relu6": false,
    "pool_cfg": 0,
    "resize_cfg": 0,
    "deconv_cfg": 0,
    "concat_cfg": 0,
    "dma_in_size": 903168,
    "dma_wgt_size": 3456,
    "wgt_per_oc_words": 0,
    "dma_out_size": 3072,
    "dma_param_count": 192,
    "tile_in_size": 9216,
    "tile_out_size": 0,
    "store_mode": 0,
    "row_cfg": 0,
    "n_input_words": 2304,
    "n_output_words": 768,
    "tile_h": 2,
    "tile_w": 4,
    "tile_num_h": 14,
    "tile_num_w": 7,
    "sched_ctrl": 1,
    "ddr_in_addr": 834519040,
    "ddr_out_addr": 835432448,
    "ddr_wgt_addr": 835424256,
    "ddr_param_addr": 835428352,
    "clamp_min": -32768,
    "clamp_max": 32767,
    "in_zp": 0,
    "input_src": -1,
    "residual_src": -1
  },
  {
    "op_type": 0,
    "data_type": 1,
    "in_h": 28,
    "in_w": 28,
    "in_c": 192,
    "out_h": 28,
    "out_w": 28,
    "out_c": 96,
    "kernel_h": 1,
    "kernel_w": 1,
    "stride_h": 1,
    "stride_w": 1,
    "pad_top": 0,
    "pad_left": 0,
    "k_depth": 192,
    "post_ctrl": 192,
    "relu6": false,
    "pool_cfg": 0,
    "resize_cfg": 0,
    "deconv_cfg": 0,
    "concat_cfg": 0,
    "dma_in_size": 354816,
    "dma_wgt_size": 36864,
    "wgt_per_oc_words": 0,
    "dma_out_size": 2304,
    "dma_param_count": 96,
    "tile_in_size": 8448,
    "tile_out_size": 0,
    "store_mode": 0,
    "row_cfg": 0,
    "n_input_words": 2112,
    "n_output_words": 576,
    "tile_h": 2,
    "tile_w": 11,
    "tile_num_h": 14,
    "tile_num_w": 3,
    "sched_ctrl": 1,
    "ddr_in_addr": 835436544,
    "ddr_out_addr": 835833856,
    "ddr_wgt_addr": 835792896,
    "ddr_param_addr": 835829760,
    "clamp_min": -32768,
    "clamp_max": 32767,
    "in_zp": 0,
    "input_src": -1,
    "residual_src": -1
  },
  {
    "op_type": 4,
    "data_type": 1,
    "in_h": 28,
    "in_w": 28,
    "in_c": 96,
    "out_h": 28,
    "out_w": 28,
    "out_c": 96,
    "kernel_h": 1,
    "kernel_w": 1,
    "stride_h": 1,
    "stride_w": 1,
    "pad_top": 0,
    "pad_left": 0,
    "k_depth": 1,
    "post_ctrl": 129,
    "relu6": false,
    "pool_cfg": 0,
    "resize_cfg": 0,
    "deconv_cfg": 0,
    "concat_cfg": 0,
    "dma_in_size": 172032,
    "dma_wgt_size": 0,
    "wgt_per_oc_words": 0,
    "dma_out_size": 3072,
    "dma_param_count": 2,
    "tile_in_size": 6144,
    "tile_out_size": 0,
    "store_mode": 0,
    "row_cfg": 0,
    "n_input_words": 1536,
    "n_output_words": 768,
    "tile_h": 4,
    "tile_w": 8,
    "tile_num_h": 7,
    "tile_num_w": 4,
    "sched_ctrl": 1,
    "ddr_in_addr": 835837952,
    "ddr_out_addr": 836190208,
    "ddr_wgt_addr": 836182016,
    "ddr_param_addr": 836186112,
    "clamp_min": -32768,
    "clamp_max": 32767,
    "in_zp": 0,
    "input_src": -1,
    "residual_src": 28,
    "add_M_A": 28577,
    "add_S_A": 15,
    "add_M_B": 21314,
    "add_S_B": 15,
    "ddr_add_b_addr": 836009984
  },
  {
    "op_type": 0,
    "data_type": 1,
    "in_h": 28,
    "in_w": 28,
    "in_c": 96,
    "out_h": 28,
    "out_w": 28,
    "out_c": 192,
    "kernel_h": 1,
    "kernel_w": 1,
    "stride_h": 1,
    "stride_w": 1,
    "pad_top": 0,
    "pad_left": 0,
    "k_depth": 96,
    "post_ctrl": 196,
    "relu6": false,
    "pool_cfg": 0,
    "resize_cfg": 0,
    "deconv_cfg": 0,
    "concat_cfg": 0,
    "dma_in_size": 172800,
    "dma_wgt_size": 36864,
    "wgt_per_oc_words": 0,
    "dma_out_size": 6144,
    "dma_param_count": 192,
    "tile_in_size": 6912,
    "tile_out_size": 0,
    "store_mode": 0,
    "row_cfg": 0,
    "n_input_words": 1728,
    "n_output_words": 1536,
    "tile_h": 6,
    "tile_w": 6,
    "tile_num_h": 5,
    "tile_num_w": 5,
    "sched_ctrl": 1,
    "ddr_in_addr": 836022272,
    "ddr_out_addr": 836239360,
    "ddr_wgt_addr": 836198400,
    "ddr_param_addr": 836235264,
    "clamp_min": -32768,
    "clamp_max": 32767,
    "in_zp": 0,
    "input_src": -1,
    "residual_src": -1
  },
  {
    "op_type": 1,
    "data_type": 1,
    "in_h": 28,
    "in_w": 28,
    "in_c": 192,
    "out_h": 28,
    "out_w": 28,
    "out_c": 192,
    "kernel_h": 3,
    "kernel_w": 3,
    "stride_h": 1,
    "stride_w": 1,
    "pad_top": 1,
    "pad_left": 1,
    "k_depth": 9,
    "post_ctrl": 196,
    "relu6": false,
    "pool_cfg": 0,
    "resize_cfg": 0,
    "deconv_cfg": 0,
    "concat_cfg": 0,
    "dma_in_size": 903168,
    "dma_wgt_size": 3456,
    "wgt_per_oc_words": 0,
    "dma_out_size": 3072,
    "dma_param_count": 192,
    "tile_in_size": 9216,
    "tile_out_size": 0,
    "store_mode": 0,
    "row_cfg": 0,
    "n_input_words": 2304,
    "n_output_words": 768,
    "tile_h": 2,
    "tile_w": 4,
    "tile_num_h": 14,
    "tile_num_w": 7,
    "sched_ctrl": 1,
    "ddr_in_addr": 836247552,
    "ddr_out_addr": 837160960,
    "ddr_wgt_addr": 837152768,
    "ddr_param_addr": 837156864,
    "clamp_min": -32768,
    "clamp_max": 32767,
    "in_zp": 0,
    "input_src": -1,
    "residual_src": -1
  },
  {
    "op_type": 0,
    "data_type": 1,
    "in_h": 28,
    "in_w": 28,
    "in_c": 192,
    "out_h": 28,
    "out_w": 28,
    "out_c": 96,
    "kernel_h": 1,
    "kernel_w": 1,
    "stride_h": 1,
    "stride_w": 1,
    "pad_top": 0,
    "pad_left": 0,
    "k_depth": 192,
    "post_ctrl": 192,
    "relu6": false,
    "pool_cfg": 0,
    "resize_cfg": 0,
    "deconv_cfg": 0,
    "concat_cfg": 0,
    "dma_in_size": 354816,
    "dma_wgt_size": 36864,
    "wgt_per_oc_words": 0,
    "dma_out_size": 2304,
    "dma_param_count": 96,
    "tile_in_size": 8448,
    "tile_out_size": 0,
    "store_mode": 0,
    "row_cfg": 0,
    "n_input_words": 2112,
    "n_output_words": 576,
    "tile_h": 2,
    "tile_w": 11,
    "tile_num_h": 14,
    "tile_num_w": 3,
    "sched_ctrl": 1,
    "ddr_in_addr": 837165056,
    "ddr_out_addr": 837562368,
    "ddr_wgt_addr": 837521408,
    "ddr_param_addr": 837558272,
    "clamp_min": -32768,
    "clamp_max": 32767,
    "in_zp": 0,
    "input_src": -1,
    "residual_src": -1
  },
  {
    "op_type": 4,
    "data_type": 1,
    "in_h": 28,
    "in_w": 28,
    "in_c": 96,
    "out_h": 28,
    "out_w": 28,
    "out_c": 96,
    "kernel_h": 1,
    "kernel_w": 1,
    "stride_h": 1,
    "stride_w": 1,
    "pad_top": 0,
    "pad_left": 0,
    "k_depth": 1,
    "post_ctrl": 129,
    "relu6": false,
    "pool_cfg": 0,
    "resize_cfg": 0,
    "deconv_cfg": 0,
    "concat_cfg": 0,
    "dma_in_size": 172032,
    "dma_wgt_size": 0,
    "wgt_per_oc_words": 0,
    "dma_out_size": 3072,
    "dma_param_count": 2,
    "tile_in_size": 6144,
    "tile_out_size": 0,
    "store_mode": 0,
    "row_cfg": 0,
    "n_input_words": 1536,
    "n_output_words": 768,
    "tile_h": 4,
    "tile_w": 8,
    "tile_num_h": 7,
    "tile_num_w": 4,
    "sched_ctrl": 1,
    "ddr_in_addr": 837566464,
    "ddr_out_addr": 837918720,
    "ddr_wgt_addr": 837910528,
    "ddr_param_addr": 837914624,
    "clamp_min": -32768,
    "clamp_max": 32767,
    "in_zp": 0,
    "input_src": -1,
    "residual_src": 32,
    "add_M_A": 31816,
    "add_S_A": 15,
    "add_M_B": 23942,
    "add_S_B": 15,
    "ddr_add_b_addr": 837738496
  },
  {
    "op_type": 0,
    "data_type": 1,
    "in_h": 28,
    "in_w": 28,
    "in_c": 96,
    "out_h": 28,
    "out_w": 28,
    "out_c": 192,
    "kernel_h": 1,
    "kernel_w": 1,
    "stride_h": 1,
    "stride_w": 1,
    "pad_top": 0,
    "pad_left": 0,
    "k_depth": 96,
    "post_ctrl": 196,
    "relu6": false,
    "pool_cfg": 0,
    "resize_cfg": 0,
    "deconv_cfg": 0,
    "concat_cfg": 0,
    "dma_in_size": 172800,
    "dma_wgt_size": 36864,
    "wgt_per_oc_words": 0,
    "dma_out_size": 6144,
    "dma_param_count": 192,
    "tile_in_size": 6912,
    "tile_out_size": 0,
    "store_mode": 0,
    "row_cfg": 0,
    "n_input_words": 1728,
    "n_output_words": 1536,
    "tile_h": 6,
    "tile_w": 6,
    "tile_num_h": 5,
    "tile_num_w": 5,
    "sched_ctrl": 1,
    "ddr_in_addr": 837750784,
    "ddr_out_addr": 837967872,
    "ddr_wgt_addr": 837926912,
    "ddr_param_addr": 837963776,
    "clamp_min": -32768,
    "clamp_max": 32767,
    "in_zp": 0,
    "input_src": -1,
    "residual_src": -1
  },
  {
    "op_type": 1,
    "data_type": 1,
    "in_h": 28,
    "in_w": 28,
    "in_c": 192,
    "out_h": 28,
    "out_w": 28,
    "out_c": 192,
    "kernel_h": 3,
    "kernel_w": 3,
    "stride_h": 1,
    "stride_w": 1,
    "pad_top": 1,
    "pad_left": 1,
    "k_depth": 9,
    "post_ctrl": 196,
    "relu6": false,
    "pool_cfg": 0,
    "resize_cfg": 0,
    "deconv_cfg": 0,
    "concat_cfg": 0,
    "dma_in_size": 903168,
    "dma_wgt_size": 3456,
    "wgt_per_oc_words": 0,
    "dma_out_size": 3072,
    "dma_param_count": 192,
    "tile_in_size": 9216,
    "tile_out_size": 0,
    "store_mode": 0,
    "row_cfg": 0,
    "n_input_words": 2304,
    "n_output_words": 768,
    "tile_h": 2,
    "tile_w": 4,
    "tile_num_h": 14,
    "tile_num_w": 7,
    "sched_ctrl": 1,
    "ddr_in_addr": 837976064,
    "ddr_out_addr": 838889472,
    "ddr_wgt_addr": 838881280,
    "ddr_param_addr": 838885376,
    "clamp_min": -32768,
    "clamp_max": 32767,
    "in_zp": 0,
    "input_src": -1,
    "residual_src": -1
  },
  {
    "op_type": 0,
    "data_type": 1,
    "in_h": 28,
    "in_w": 28,
    "in_c": 192,
    "out_h": 28,
    "out_w": 28,
    "out_c": 96,
    "kernel_h": 1,
    "kernel_w": 1,
    "stride_h": 1,
    "stride_w": 1,
    "pad_top": 0,
    "pad_left": 0,
    "k_depth": 192,
    "post_ctrl": 192,
    "relu6": false,
    "pool_cfg": 0,
    "resize_cfg": 0,
    "deconv_cfg": 0,
    "concat_cfg": 0,
    "dma_in_size": 354816,
    "dma_wgt_size": 36864,
    "wgt_per_oc_words": 0,
    "dma_out_size": 2304,
    "dma_param_count": 96,
    "tile_in_size": 8448,
    "tile_out_size": 0,
    "store_mode": 0,
    "row_cfg": 0,
    "n_input_words": 2112,
    "n_output_words": 576,
    "tile_h": 2,
    "tile_w": 11,
    "tile_num_h": 14,
    "tile_num_w": 3,
    "sched_ctrl": 1,
    "ddr_in_addr": 838893568,
    "ddr_out_addr": 839290880,
    "ddr_wgt_addr": 839249920,
    "ddr_param_addr": 839286784,
    "clamp_min": -32768,
    "clamp_max": 32767,
    "in_zp": 0,
    "input_src": -1,
    "residual_src": -1
  },
  {
    "op_type": 4,
    "data_type": 1,
    "in_h": 28,
    "in_w": 28,
    "in_c": 96,
    "out_h": 28,
    "out_w": 28,
    "out_c": 96,
    "kernel_h": 1,
    "kernel_w": 1,
    "stride_h": 1,
    "stride_w": 1,
    "pad_top": 0,
    "pad_left": 0,
    "k_depth": 1,
    "post_ctrl": 129,
    "relu6": false,
    "pool_cfg": 0,
    "resize_cfg": 0,
    "deconv_cfg": 0,
    "concat_cfg": 0,
    "dma_in_size": 172032,
    "dma_wgt_size": 0,
    "wgt_per_oc_words": 0,
    "dma_out_size": 3072,
    "dma_param_count": 2,
    "tile_in_size": 6144,
    "tile_out_size": 0,
    "store_mode": 0,
    "row_cfg": 0,
    "n_input_words": 1536,
    "n_output_words": 768,
    "tile_h": 4,
    "tile_w": 8,
    "tile_num_h": 7,
    "tile_num_w": 4,
    "sched_ctrl": 1,
    "ddr_in_addr": 839294976,
    "ddr_out_addr": 839647232,
    "ddr_wgt_addr": 839639040,
    "ddr_param_addr": 839643136,
    "clamp_min": -32768,
    "clamp_max": 32767,
    "in_zp": 0,
    "input_src": -1,
    "residual_src": 36,
    "add_M_A": 19237,
    "add_S_A": 15,
    "add_M_B": 24803,
    "add_S_B": 15,
    "ddr_add_b_addr": 839467008
  },
  {
    "op_type": 0,
    "data_type": 1,
    "in_h": 28,
    "in_w": 28,
    "in_c": 96,
    "out_h": 28,
    "out_w": 28,
    "out_c": 192,
    "kernel_h": 1,
    "kernel_w": 1,
    "stride_h": 1,
    "stride_w": 1,
    "pad_top": 0,
    "pad_left": 0,
    "k_depth": 96,
    "post_ctrl": 196,
    "relu6": false,
    "pool_cfg": 0,
    "resize_cfg": 0,
    "deconv_cfg": 0,
    "concat_cfg": 0,
    "dma_in_size": 172800,
    "dma_wgt_size": 36864,
    "wgt_per_oc_words": 0,
    "dma_out_size": 6144,
    "dma_param_count": 192,
    "tile_in_size": 6912,
    "tile_out_size": 0,
    "store_mode": 0,
    "row_cfg": 0,
    "n_input_words": 1728,
    "n_output_words": 1536,
    "tile_h": 6,
    "tile_w": 6,
    "tile_num_h": 5,
    "tile_num_w": 5,
    "sched_ctrl": 1,
    "ddr_in_addr": 839479296,
    "ddr_out_addr": 839696384,
    "ddr_wgt_addr": 839655424,
    "ddr_param_addr": 839692288,
    "clamp_min": -32768,
    "clamp_max": 32767,
    "in_zp": 0,
    "input_src": -1,
    "residual_src": -1
  },
  {
    "op_type": 1,
    "data_type": 1,
    "in_h": 28,
    "in_w": 28,
    "in_c": 192,
    "out_h": 28,
    "out_w": 28,
    "out_c": 192,
    "kernel_h": 3,
    "kernel_w": 3,
    "stride_h": 1,
    "stride_w": 1,
    "pad_top": 1,
    "pad_left": 1,
    "k_depth": 9,
    "post_ctrl": 196,
    "relu6": false,
    "pool_cfg": 0,
    "resize_cfg": 0,
    "deconv_cfg": 0,
    "concat_cfg": 0,
    "dma_in_size": 903168,
    "dma_wgt_size": 3456,
    "wgt_per_oc_words": 0,
    "dma_out_size": 3072,
    "dma_param_count": 192,
    "tile_in_size": 9216,
    "tile_out_size": 0,
    "store_mode": 0,
    "row_cfg": 0,
    "n_input_words": 2304,
    "n_output_words": 768,
    "tile_h": 2,
    "tile_w": 4,
    "tile_num_h": 14,
    "tile_num_w": 7,
    "sched_ctrl": 1,
    "ddr_in_addr": 839704576,
    "ddr_out_addr": 840617984,
    "ddr_wgt_addr": 840609792,
    "ddr_param_addr": 840613888,
    "clamp_min": -32768,
    "clamp_max": 32767,
    "in_zp": 0,
    "input_src": -1,
    "residual_src": -1
  },
  {
    "op_type": 0,
    "data_type": 1,
    "in_h": 28,
    "in_w": 28,
    "in_c": 192,
    "out_h": 28,
    "out_w": 28,
    "out_c": 96,
    "kernel_h": 1,
    "kernel_w": 1,
    "stride_h": 1,
    "stride_w": 1,
    "pad_top": 0,
    "pad_left": 0,
    "k_depth": 192,
    "post_ctrl": 192,
    "relu6": false,
    "pool_cfg": 0,
    "resize_cfg": 0,
    "deconv_cfg": 0,
    "concat_cfg": 0,
    "dma_in_size": 354816,
    "dma_wgt_size": 36864,
    "wgt_per_oc_words": 0,
    "dma_out_size": 2304,
    "dma_param_count": 96,
    "tile_in_size": 8448,
    "tile_out_size": 0,
    "store_mode": 0,
    "row_cfg": 0,
    "n_input_words": 2112,
    "n_output_words": 576,
    "tile_h": 2,
    "tile_w": 11,
    "tile_num_h": 14,
    "tile_num_w": 3,
    "sched_ctrl": 1,
    "ddr_in_addr": 840622080,
    "ddr_out_addr": 841019392,
    "ddr_wgt_addr": 840978432,
    "ddr_param_addr": 841015296,
    "clamp_min": -32768,
    "clamp_max": 32767,
    "in_zp": 0,
    "input_src": -1,
    "residual_src": -1
  },
  {
    "op_type": 4,
    "data_type": 1,
    "in_h": 28,
    "in_w": 28,
    "in_c": 96,
    "out_h": 28,
    "out_w": 28,
    "out_c": 96,
    "kernel_h": 1,
    "kernel_w": 1,
    "stride_h": 1,
    "stride_w": 1,
    "pad_top": 0,
    "pad_left": 0,
    "k_depth": 1,
    "post_ctrl": 129,
    "relu6": false,
    "pool_cfg": 0,
    "resize_cfg": 0,
    "deconv_cfg": 0,
    "concat_cfg": 0,
    "dma_in_size": 172032,
    "dma_wgt_size": 0,
    "wgt_per_oc_words": 0,
    "dma_out_size": 3072,
    "dma_param_count": 2,
    "tile_in_size": 6144,
    "tile_out_size": 0,
    "store_mode": 0,
    "row_cfg": 0,
    "n_input_words": 1536,
    "n_output_words": 768,
    "tile_h": 4,
    "tile_w": 8,
    "tile_num_h": 7,
    "tile_num_w": 4,
    "sched_ctrl": 1,
    "ddr_in_addr": 841023488,
    "ddr_out_addr": 841375744,
    "ddr_wgt_addr": 841367552,
    "ddr_param_addr": 841371648,
    "clamp_min": -32768,
    "clamp_max": 32767,
    "in_zp": 0,
    "input_src": -1,
    "residual_src": 40,
    "add_M_A": 17876,
    "add_S_A": 15,
    "add_M_B": 26013,
    "add_S_B": 15,
    "ddr_add_b_addr": 841195520
  },
  {
    "op_type": 0,
    "data_type": 1,
    "in_h": 28,
    "in_w": 28,
    "in_c": 96,
    "out_h": 28,
    "out_w": 28,
    "out_c": 192,
    "kernel_h": 1,
    "kernel_w": 1,
    "stride_h": 1,
    "stride_w": 1,
    "pad_top": 0,
    "pad_left": 0,
    "k_depth": 96,
    "post_ctrl": 196,
    "relu6": false,
    "pool_cfg": 0,
    "resize_cfg": 0,
    "deconv_cfg": 0,
    "concat_cfg": 0,
    "dma_in_size": 172800,
    "dma_wgt_size": 36864,
    "wgt_per_oc_words": 0,
    "dma_out_size": 6144,
    "dma_param_count": 192,
    "tile_in_size": 6912,
    "tile_out_size": 0,
    "store_mode": 0,
    "row_cfg": 0,
    "n_input_words": 1728,
    "n_output_words": 1536,
    "tile_h": 6,
    "tile_w": 6,
    "tile_num_h": 5,
    "tile_num_w": 5,
    "sched_ctrl": 1,
    "ddr_in_addr": 841207808,
    "ddr_out_addr": 841424896,
    "ddr_wgt_addr": 841383936,
    "ddr_param_addr": 841420800,
    "clamp_min": -32768,
    "clamp_max": 32767,
    "in_zp": 0,
    "input_src": -1,
    "residual_src": -1
  },
  {
    "op_type": 1,
    "data_type": 1,
    "in_h": 28,
    "in_w": 28,
    "in_c": 192,
    "out_h": 28,
    "out_w": 28,
    "out_c": 192,
    "kernel_h": 3,
    "kernel_w": 3,
    "stride_h": 1,
    "stride_w": 1,
    "pad_top": 1,
    "pad_left": 1,
    "k_depth": 9,
    "post_ctrl": 196,
    "relu6": false,
    "pool_cfg": 0,
    "resize_cfg": 0,
    "deconv_cfg": 0,
    "concat_cfg": 0,
    "dma_in_size": 903168,
    "dma_wgt_size": 3456,
    "wgt_per_oc_words": 0,
    "dma_out_size": 3072,
    "dma_param_count": 192,
    "tile_in_size": 9216,
    "tile_out_size": 0,
    "store_mode": 0,
    "row_cfg": 0,
    "n_input_words": 2304,
    "n_output_words": 768,
    "tile_h": 2,
    "tile_w": 4,
    "tile_num_h": 14,
    "tile_num_w": 7,
    "sched_ctrl": 1,
    "ddr_in_addr": 841433088,
    "ddr_out_addr": 842346496,
    "ddr_wgt_addr": 842338304,
    "ddr_param_addr": 842342400,
    "clamp_min": -32768,
    "clamp_max": 32767,
    "in_zp": 0,
    "input_src": -1,
    "residual_src": -1
  },
  {
    "op_type": 0,
    "data_type": 1,
    "in_h": 28,
    "in_w": 28,
    "in_c": 192,
    "out_h": 28,
    "out_w": 28,
    "out_c": 96,
    "kernel_h": 1,
    "kernel_w": 1,
    "stride_h": 1,
    "stride_w": 1,
    "pad_top": 0,
    "pad_left": 0,
    "k_depth": 192,
    "post_ctrl": 192,
    "relu6": false,
    "pool_cfg": 0,
    "resize_cfg": 0,
    "deconv_cfg": 0,
    "concat_cfg": 0,
    "dma_in_size": 354816,
    "dma_wgt_size": 36864,
    "wgt_per_oc_words": 0,
    "dma_out_size": 2304,
    "dma_param_count": 96,
    "tile_in_size": 8448,
    "tile_out_size": 0,
    "store_mode": 0,
    "row_cfg": 0,
    "n_input_words": 2112,
    "n_output_words": 576,
    "tile_h": 2,
    "tile_w": 11,
    "tile_num_h": 14,
    "tile_num_w": 3,
    "sched_ctrl": 1,
    "ddr_in_addr": 842350592,
    "ddr_out_addr": 842747904,
    "ddr_wgt_addr": 842706944,
    "ddr_param_addr": 842743808,
    "clamp_min": -32768,
    "clamp_max": 32767,
    "in_zp": 0,
    "input_src": -1,
    "residual_src": -1
  },
  {
    "op_type": 4,
    "data_type": 1,
    "in_h": 28,
    "in_w": 28,
    "in_c": 96,
    "out_h": 28,
    "out_w": 28,
    "out_c": 96,
    "kernel_h": 1,
    "kernel_w": 1,
    "stride_h": 1,
    "stride_w": 1,
    "pad_top": 0,
    "pad_left": 0,
    "k_depth": 1,
    "post_ctrl": 129,
    "relu6": false,
    "pool_cfg": 0,
    "resize_cfg": 0,
    "deconv_cfg": 0,
    "concat_cfg": 0,
    "dma_in_size": 172032,
    "dma_wgt_size": 0,
    "wgt_per_oc_words": 0,
    "dma_out_size": 3072,
    "dma_param_count": 2,
    "tile_in_size": 6144,
    "tile_out_size": 0,
    "store_mode": 0,
    "row_cfg": 0,
    "n_input_words": 1536,
    "n_output_words": 768,
    "tile_h": 4,
    "tile_w": 8,
    "tile_num_h": 7,
    "tile_num_w": 4,
    "sched_ctrl": 1,
    "ddr_in_addr": 842752000,
    "ddr_out_addr": 843104256,
    "ddr_wgt_addr": 843096064,
    "ddr_param_addr": 843100160,
    "clamp_min": -32768,
    "clamp_max": 32767,
    "in_zp": 0,
    "input_src": -1,
    "residual_src": 44,
    "add_M_A": 18516,
    "add_S_A": 15,
    "add_M_B": 25213,
    "add_S_B": 15,
    "ddr_add_b_addr": 842924032
  },
  {
    "op_type": 0,
    "data_type": 1,
    "in_h": 28,
    "in_w": 28,
    "in_c": 96,
    "out_h": 28,
    "out_w": 28,
    "out_c": 384,
    "kernel_h": 1,
    "kernel_w": 1,
    "stride_h": 1,
    "stride_w": 1,
    "pad_top": 0,
    "pad_left": 0,
    "k_depth": 96,
    "post_ctrl": 196,
    "relu6": false,
    "pool_cfg": 0,
    "resize_cfg": 0,
    "deconv_cfg": 0,
    "concat_cfg": 0,
    "dma_in_size": 247296,
    "dma_wgt_size": 73728,
    "wgt_per_oc_words": 0,
    "dma_out_size": 3840,
    "dma_param_count": 384,
    "tile_in_size": 4416,
    "tile_out_size": 0,
    "store_mode": 0,
    "row_cfg": 0,
    "n_input_words": 1104,
    "n_output_words": 960,
    "tile_h": 1,
    "tile_w": 23,
    "tile_num_h": 28,
    "tile_num_w": 2,
    "sched_ctrl": 1,
    "ddr_in_addr": 842936320,
    "ddr_out_addr": 843268096,
    "ddr_wgt_addr": 843186176,
    "ddr_param_addr": 843259904,
    "clamp_min": -32768,
    "clamp_max": 32767,
    "in_zp": 0,
    "input_src": -1,
    "residual_src": -1
  },
  {
    "op_type": 1,
    "data_type": 1,
    "in_h": 28,
    "in_w": 28,
    "in_c": 384,
    "out_h": 14,
    "out_w": 14,
    "out_c": 384,
    "kernel_h": 3,
    "kernel_w": 3,
    "stride_h": 2,
    "stride_w": 2,
    "pad_top": 1,
    "pad_left": 1,
    "k_depth": 9,
    "post_ctrl": 196,
    "relu6": false,
    "pool_cfg": 0,
    "resize_cfg": 0,
    "deconv_cfg": 0,
    "concat_cfg": 0,
    "dma_in_size": 1354752,
    "dma_wgt_size": 6912,
    "wgt_per_oc_words": 0,
    "dma_out_size": 768,
    "dma_param_count": 384,
    "tile_in_size": 6912,
    "tile_out_size": 0,
    "store_mode": 0,
    "row_cfg": 0,
    "n_input_words": 1728,
    "n_output_words": 192,
    "tile_h": 1,
    "tile_w": 1,
    "tile_num_h": 14,
    "tile_num_w": 14,
    "sched_ctrl": 1,
    "ddr_in_addr": 843272192,
    "ddr_out_addr": 844644352,
    "ddr_wgt_addr": 844627968,
    "ddr_param_addr": 844636160,
    "clamp_min": -32768,
    "clamp_max": 32767,
    "in_zp": 0,
    "input_src": -1,
    "residual_src": -1
  },
  {
    "op_type": 0,
    "data_type": 1,
    "in_h": 14,
    "in_w": 14,
    "in_c": 384,
    "out_h": 14,
    "out_w": 14,
    "out_c": 96,
    "kernel_h": 1,
    "kernel_w": 1,
    "stride_h": 1,
    "stride_w": 1,
    "pad_top": 0,
    "pad_left": 0,
    "k_depth": 384,
    "post_ctrl": 192,
    "relu6": false,
    "pool_cfg": 0,
    "resize_cfg": 0,
    "deconv_cfg": 0,
    "concat_cfg": 0,
    "dma_in_size": 150528,
    "dma_wgt_size": 73728,
    "wgt_per_oc_words": 0,
    "dma_out_size": 2688,
    "dma_param_count": 96,
    "tile_in_size": 10752,
    "tile_out_size": 0,
    "store_mode": 0,
    "row_cfg": 0,
    "n_input_words": 2688,
    "n_output_words": 672,
    "tile_h": 2,
    "tile_w": 7,
    "tile_num_h": 7,
    "tile_num_w": 2,
    "sched_ctrl": 1,
    "ddr_in_addr": 844648448,
    "ddr_out_addr": 844877824,
    "ddr_wgt_addr": 844800000,
    "ddr_param_addr": 844873728,
    "clamp_min": -32768,
    "clamp_max": 32767,
    "in_zp": 0,
    "input_src": -1,
    "residual_src": -1
  },
  {
    "op_type": 0,
    "data_type": 1,
    "in_h": 14,
    "in_w": 14,
    "in_c": 96,
    "out_h": 14,
    "out_w": 14,
    "out_c": 192,
    "kernel_h": 1,
    "kernel_w": 1,
    "stride_h": 1,
    "stride_w": 1,
    "pad_top": 0,
    "pad_left": 0,
    "k_depth": 96,
    "post_ctrl": 196,
    "relu6": false,
    "pool_cfg": 0,
    "resize_cfg": 0,
    "deconv_cfg": 0,
    "concat_cfg": 0,
    "dma_in_size": 62208,
    "dma_wgt_size": 36864,
    "wgt_per_oc_words": 0,
    "dma_out_size": 1536,
    "dma_param_count": 192,
    "tile_in_size": 6912,
    "tile_out_size": 0,
    "store_mode": 0,
    "row_cfg": 0,
    "n_input_words": 1728,
    "n_output_words": 384,
    "tile_h": 6,
    "tile_w": 6,
    "tile_num_h": 3,
    "tile_num_w": 3,
    "sched_ctrl": 1,
    "ddr_in_addr": 844881920,
    "ddr_out_addr": 844988416,
    "ddr_wgt_addr": 844947456,
    "ddr_param_addr": 844984320,
    "clamp_min": -32768,
    "clamp_max": 32767,
    "in_zp": 0,
    "input_src": -1,
    "residual_src": -1
  },
  {
    "op_type": 1,
    "data_type": 1,
    "in_h": 14,
    "in_w": 14,
    "in_c": 192,
    "out_h": 14,
    "out_w": 14,
    "out_c": 192,
    "kernel_h": 3,
    "kernel_w": 3,
    "stride_h": 1,
    "stride_w": 1,
    "pad_top": 1,
    "pad_left": 1,
    "k_depth": 9,
    "post_ctrl": 196,
    "relu6": false,
    "pool_cfg": 0,
    "resize_cfg": 0,
    "deconv_cfg": 0,
    "concat_cfg": 0,
    "dma_in_size": 258048,
    "dma_wgt_size": 3456,
    "wgt_per_oc_words": 0,
    "dma_out_size": 1536,
    "dma_param_count": 192,
    "tile_in_size": 9216,
    "tile_out_size": 0,
    "store_mode": 0,
    "row_cfg": 0,
    "n_input_words": 2304,
    "n_output_words": 384,
    "tile_h": 2,
    "tile_w": 4,
    "tile_num_h": 7,
    "tile_num_w": 4,
    "sched_ctrl": 1,
    "ddr_in_addr": 844992512,
    "ddr_out_addr": 845258752,
    "ddr_wgt_addr": 845250560,
    "ddr_param_addr": 845254656,
    "clamp_min": -32768,
    "clamp_max": 32767,
    "in_zp": 0,
    "input_src": -1,
    "residual_src": -1
  },
  {
    "op_type": 0,
    "data_type": 1,
    "in_h": 14,
    "in_w": 14,
    "in_c": 192,
    "out_h": 14,
    "out_w": 14,
    "out_c": 96,
    "kernel_h": 1,
    "kernel_w": 1,
    "stride_h": 1,
    "stride_w": 1,
    "pad_top": 0,
    "pad_left": 0,
    "k_depth": 192,
    "post_ctrl": 192,
    "relu6": false,
    "pool_cfg": 0,
    "resize_cfg": 0,
    "deconv_cfg": 0,
    "concat_cfg": 0,
    "dma_in_size": 118272,
    "dma_wgt_size": 36864,
    "wgt_per_oc_words": 0,
    "dma_out_size": 1152,
    "dma_param_count": 96,
    "tile_in_size": 8448,
    "tile_out_size": 0,
    "store_mode": 0,
    "row_cfg": 0,
    "n_input_words": 2112,
    "n_output_words": 288,
    "tile_h": 2,
    "tile_w": 11,
    "tile_num_h": 7,
    "tile_num_w": 2,
    "sched_ctrl": 1,
    "ddr_in_addr": 845262848,
    "ddr_out_addr": 845422592,
    "ddr_wgt_addr": 845381632,
    "ddr_param_addr": 845418496,
    "clamp_min": -32768,
    "clamp_max": 32767,
    "in_zp": 0,
    "input_src": -1,
    "residual_src": -1
  },
  {
    "op_type": 4,
    "data_type": 1,
    "in_h": 14,
    "in_w": 14,
    "in_c": 96,
    "out_h": 14,
    "out_w": 14,
    "out_c": 96,
    "kernel_h": 1,
    "kernel_w": 1,
    "stride_h": 1,
    "stride_w": 1,
    "pad_top": 0,
    "pad_left": 0,
    "k_depth": 1,
    "post_ctrl": 129,
    "relu6": false,
    "pool_cfg": 0,
    "resize_cfg": 0,
    "deconv_cfg": 0,
    "concat_cfg": 0,
    "dma_in_size": 49152,
    "dma_wgt_size": 0,
    "wgt_per_oc_words": 0,
    "dma_out_size": 2304,
    "dma_param_count": 2,
    "tile_in_size": 6144,
    "tile_out_size": 0,
    "store_mode": 0,
    "row_cfg": 0,
    "n_input_words": 1536,
    "n_output_words": 576,
    "tile_h": 4,
    "tile_w": 8,
    "tile_num_h": 4,
    "tile_num_w": 2,
    "sched_ctrl": 1,
    "ddr_in_addr": 845426688,
    "ddr_out_addr": 845533184,
    "ddr_wgt_addr": 845524992,
    "ddr_param_addr": 845529088,
    "clamp_min": -32768,
    "clamp_max": 32767,
    "in_zp": 0,
    "input_src": -1,
    "residual_src": 51,
    "add_M_A": 22319,
    "add_S_A": 15,
    "add_M_B": 23718,
    "add_S_B": 15,
    "ddr_add_b_addr": 845475840
  },
  {
    "op_type": 0,
    "data_type": 1,
    "in_h": 14,
    "in_w": 14,
    "in_c": 96,
    "out_h": 14,
    "out_w": 14,
    "out_c": 192,
    "kernel_h": 1,
    "kernel_w": 1,
    "stride_h": 1,
    "stride_w": 1,
    "pad_top": 0,
    "pad_left": 0,
    "k_depth": 96,
    "post_ctrl": 196,
    "relu6": false,
    "pool_cfg": 0,
    "resize_cfg": 0,
    "deconv_cfg": 0,
    "concat_cfg": 0,
    "dma_in_size": 62208,
    "dma_wgt_size": 36864,
    "wgt_per_oc_words": 0,
    "dma_out_size": 1536,
    "dma_param_count": 192,
    "tile_in_size": 6912,
    "tile_out_size": 0,
    "store_mode": 0,
    "row_cfg": 0,
    "n_input_words": 1728,
    "n_output_words": 384,
    "tile_h": 6,
    "tile_w": 6,
    "tile_num_h": 3,
    "tile_num_w": 3,
    "sched_ctrl": 1,
    "ddr_in_addr": 845488128,
    "ddr_out_addr": 845594624,
    "ddr_wgt_addr": 845553664,
    "ddr_param_addr": 845590528,
    "clamp_min": -32768,
    "clamp_max": 32767,
    "in_zp": 0,
    "input_src": -1,
    "residual_src": -1
  },
  {
    "op_type": 1,
    "data_type": 1,
    "in_h": 14,
    "in_w": 14,
    "in_c": 192,
    "out_h": 14,
    "out_w": 14,
    "out_c": 192,
    "kernel_h": 3,
    "kernel_w": 3,
    "stride_h": 1,
    "stride_w": 1,
    "pad_top": 1,
    "pad_left": 1,
    "k_depth": 9,
    "post_ctrl": 196,
    "relu6": false,
    "pool_cfg": 0,
    "resize_cfg": 0,
    "deconv_cfg": 0,
    "concat_cfg": 0,
    "dma_in_size": 258048,
    "dma_wgt_size": 3456,
    "wgt_per_oc_words": 0,
    "dma_out_size": 1536,
    "dma_param_count": 192,
    "tile_in_size": 9216,
    "tile_out_size": 0,
    "store_mode": 0,
    "row_cfg": 0,
    "n_input_words": 2304,
    "n_output_words": 384,
    "tile_h": 2,
    "tile_w": 4,
    "tile_num_h": 7,
    "tile_num_w": 4,
    "sched_ctrl": 1,
    "ddr_in_addr": 845598720,
    "ddr_out_addr": 845864960,
    "ddr_wgt_addr": 845856768,
    "ddr_param_addr": 845860864,
    "clamp_min": -32768,
    "clamp_max": 32767,
    "in_zp": 0,
    "input_src": -1,
    "residual_src": -1
  },
  {
    "op_type": 0,
    "data_type": 1,
    "in_h": 14,
    "in_w": 14,
    "in_c": 192,
    "out_h": 14,
    "out_w": 14,
    "out_c": 96,
    "kernel_h": 1,
    "kernel_w": 1,
    "stride_h": 1,
    "stride_w": 1,
    "pad_top": 0,
    "pad_left": 0,
    "k_depth": 192,
    "post_ctrl": 192,
    "relu6": false,
    "pool_cfg": 0,
    "resize_cfg": 0,
    "deconv_cfg": 0,
    "concat_cfg": 0,
    "dma_in_size": 118272,
    "dma_wgt_size": 36864,
    "wgt_per_oc_words": 0,
    "dma_out_size": 1152,
    "dma_param_count": 96,
    "tile_in_size": 8448,
    "tile_out_size": 0,
    "store_mode": 0,
    "row_cfg": 0,
    "n_input_words": 2112,
    "n_output_words": 288,
    "tile_h": 2,
    "tile_w": 11,
    "tile_num_h": 7,
    "tile_num_w": 2,
    "sched_ctrl": 1,
    "ddr_in_addr": 845869056,
    "ddr_out_addr": 846028800,
    "ddr_wgt_addr": 845987840,
    "ddr_param_addr": 846024704,
    "clamp_min": -32768,
    "clamp_max": 32767,
    "in_zp": 0,
    "input_src": -1,
    "residual_src": -1
  },
  {
    "op_type": 4,
    "data_type": 1,
    "in_h": 14,
    "in_w": 14,
    "in_c": 96,
    "out_h": 14,
    "out_w": 14,
    "out_c": 96,
    "kernel_h": 1,
    "kernel_w": 1,
    "stride_h": 1,
    "stride_w": 1,
    "pad_top": 0,
    "pad_left": 0,
    "k_depth": 1,
    "post_ctrl": 129,
    "relu6": false,
    "pool_cfg": 0,
    "resize_cfg": 0,
    "deconv_cfg": 0,
    "concat_cfg": 0,
    "dma_in_size": 49152,
    "dma_wgt_size": 0,
    "wgt_per_oc_words": 0,
    "dma_out_size": 2304,
    "dma_param_count": 2,
    "tile_in_size": 6144,
    "tile_out_size": 0,
    "store_mode": 0,
    "row_cfg": 0,
    "n_input_words": 1536,
    "n_output_words": 576,
    "tile_h": 4,
    "tile_w": 8,
    "tile_num_h": 4,
    "tile_num_w": 2,
    "sched_ctrl": 1,
    "ddr_in_addr": 846032896,
    "ddr_out_addr": 846139392,
    "ddr_wgt_addr": 846131200,
    "ddr_param_addr": 846135296,
    "clamp_min": -32768,
    "clamp_max": 32767,
    "in_zp": 0,
    "input_src": -1,
    "residual_src": 55,
    "add_M_A": 27643,
    "add_S_A": 15,
    "add_M_B": 25819,
    "add_S_B": 15,
    "ddr_add_b_addr": 846082048
  },
  {
    "op_type": 0,
    "data_type": 1,
    "in_h": 14,
    "in_w": 14,
    "in_c": 96,
    "out_h": 14,
    "out_w": 14,
    "out_c": 512,
    "kernel_h": 1,
    "kernel_w": 1,
    "stride_h": 1,
    "stride_w": 1,
    "pad_top": 0,
    "pad_left": 0,
    "k_depth": 96,
    "post_ctrl": 196,
    "relu6": false,
    "pool_cfg": 0,
    "resize_cfg": 0,
    "deconv_cfg": 0,
    "concat_cfg": 0,
    "dma_in_size": 59136,
    "dma_wgt_size": 98304,
    "wgt_per_oc_words": 0,
    "dma_out_size": 6144,
    "dma_param_count": 512,
    "tile_in_size": 4224,
    "tile_out_size": 0,
    "store_mode": 0,
    "row_cfg": 0,
    "n_input_words": 1056,
    "n_output_words": 1536,
    "tile_h": 2,
    "tile_w": 11,
    "tile_num_h": 7,
    "tile_num_w": 2,
    "sched_ctrl": 1,
    "ddr_in_addr": 846094336,
    "ddr_out_addr": 846262272,
    "ddr_wgt_addr": 846155776,
    "ddr_param_addr": 846254080,
    "clamp_min": -32768,
    "clamp_max": 32767,
    "in_zp": 0,
    "input_src": -1,
    "residual_src": -1
  },
  {
    "op_type": 1,
    "data_type": 1,
    "in_h": 14,
    "in_w": 14,
    "in_c": 512,
    "out_h": 1,
    "out_w": 1,
    "out_c": 512,
    "kernel_h": 14,
    "kernel_w": 14,
    "stride_h": 1,
    "stride_w": 1,
    "pad_top": 0,
    "pad_left": 0,
    "k_depth": 196,
    "post_ctrl": 192,
    "relu6": false,
    "pool_cfg": 0,
    "resize_cfg": 0,
    "deconv_cfg": 0,
    "concat_cfg": 0,
    "dma_in_size": 200704,
    "dma_wgt_size": 200704,
    "wgt_per_oc_words": 0,
    "dma_out_size": 1024,
    "dma_param_count": 512,
    "tile_in_size": 0,
    "tile_out_size": 0,
    "store_mode": 0,
    "row_cfg": 0,
    "n_input_words": 50176,
    "n_output_words": 256,
    "tile_h": 0,
    "tile_w": 0,
    "tile_num_h": 0,
    "tile_num_w": 0,
    "sched_ctrl": 0,
    "ddr_in_addr": 846270464,
    "ddr_out_addr": 846680064,
    "ddr_wgt_addr": 846471168,
    "ddr_param_addr": 846671872,
    "clamp_min": -32768,
    "clamp_max": 32767,
    "in_zp": 0,
    "input_src": -1,
    "residual_src": -1
  },
  {
    "op_type": 0,
    "data_type": 1,
    "in_h": 1,
    "in_w": 1,
    "in_c": 512,
    "out_h": 1,
    "out_w": 1,
    "out_c": 512,
    "kernel_h": 1,
    "kernel_w": 1,
    "stride_h": 1,
    "stride_w": 1,
    "pad_top": 0,
    "pad_left": 0,
    "k_depth": 512,
    "post_ctrl": 192,
    "relu6": false,
    "pool_cfg": 0,
    "resize_cfg": 0,
    "deconv_cfg": 0,
    "concat_cfg": 0,
    "dma_in_size": 1024,
    "dma_wgt_size": 524288,
    "wgt_per_oc_words": 4096,
    "dma_out_size": 1024,
    "dma_param_count": 512,
    "tile_in_size": 1024,
    "tile_out_size": 0,
    "store_mode": 0,
    "row_cfg": 0,
    "n_input_words": 256,
    "n_output_words": 256,
    "tile_h": 1,
    "tile_w": 1,
    "tile_num_h": 1,
    "tile_num_w": 1,
    "sched_ctrl": 1,
    "ddr_in_addr": 846684160,
    "ddr_out_addr": 847220736,
    "ddr_wgt_addr": 846688256,
    "ddr_param_addr": 847212544,
    "clamp_min": -32768,
    "clamp_max": 32767,
    "in_zp": 0,
    "input_src": -1,
    "residual_src": -1
  }
]